{"guide_git_commit.md":"6b412a61","guide_git_article_ssh-config.md":"006f7015","guide_index.md":"ffb614e0","guide_git_basic.md":"4b7835b8","guide_interview_algorithm.md":"d2441008","guide_interview_enter-url-happens.md":"3ff7c5c0","guide_css_basic.md":"50e96dce","guide_css_framework.md":"91d89a96","guide_deploy_github-actions.md":"dd993afa","guide_git_article_end-of-line.md":"669f6e4f","guide_react_basic.md":"f55427fe","guide_javascript_expand.md":"fb287978","guide_vscode_basic.md":"dfe1cfde","guide_vscode_extensions.md":"97d6015b","guide_vue_directives.md":"d15f103a","guide_typescript_basic.md":"d89a409c","guide_vue_components.md":"bc830950","guide_nuxt_basic.md":"e6ee6b4f","guide_javascript_basic.md":"d1115d04","guide_markdown_basic.md":"a58df5ea","guide_node_basic.md":"3ca9d2d7","guide_interview_index.md":"512dce2b","guide_react_expand.md":"7a4df0c1","guide_vscode_config.md":"95d89417","guide_typescript_utils.md":"7e33825d","guide_typescript_directives.md":"67d430bb","notes_collection_keyboard-shortcuts.md":"58040780","notes_collection_article.md":"96080d0d","index.md":"512df1c9","guide_javascript_utils.md":"6d0fb65d","guide_webpack_basic.md":"ff545f2b","guide_vue_expand.md":"5138fa0b","guide_vue_basic.md":"0fb55342","notes_others_reproduction.md":"6e30feb2","notes_others_changelog.md":"0509aaca","notes_read_excerpt.md":"2b4c298d","notes_travel_cycling.md":"2864b1f8","notes_summary_2023.md":"bce8ed64","notes_read_writing.md":"53d6059e","notes_read_poetry.md":"1cd8c47c","notes_read_notebook.md":"92625a05","notes_read_dragon-raja.md":"dd3462ee","notes_others_share.md":"50b38542","notes_index.md":"24d7d497"}
